LICENSE
README.md
setup.py
altair_ally/__init__.py
altair_ally/eda_plots.py
altair_ally.egg-info/PKG-INFO
altair_ally.egg-info/SOURCES.txt
altair_ally.egg-info/dependency_links.txt
altair_ally.egg-info/requires.txt
altair_ally.egg-info/top_level.txt
tests/test_eda_plots.py