Metadata-Version: 2.1
Name: altair_ally
Version: 0.1.1
Summary: Altair Ally is a companion package to Altair, which provides shortcuts to create common plots for exploratory data analysis, particularly those involving visualization of an entire dataset.
Home-page: https://joelostblom.github.io/altair_ally
Author: Joel Ostblom
Author-email: joel.ostblom@protonmail.com
License: BSD-3
Requires-Python: >=3.6
License-File: LICENSE
Requires-Dist: altair
Requires-Dist: vega_datasets
Requires-Dist: pandas
